{
  "epic_key": "NCRM-374",
  "epic_name": "Owners amendments",
  "project_key": "NCRM",
  "project_name": "NawyCRM",
  "epic_created": "2024-04-07T11:15:56.596+0200",
  "generated_at": "2026-07-16T16:22:04.054435",
  "rate_per_day_egp": 3500.0,
  "total_tickets": 19,
  "complete_tickets": 19,
  "in_progress_tickets": 0,
  "total_net_days": 219.88,
  "total_cost_egp": 769580.0,
  "tickets": [
    {
      "key": "NCRM-376",
      "summary": "owner statuses Manual change",
      "status": "Done",
      "net_days": 28.61,
      "gross_days": 28.61,
      "excluded_days": 0.0,
      "cost_egp": 100135.0,
      "is_complete": true,
      "num_spans": 1
    },
    {
      "key": "NCRM-377",
      "summary": "Ability to remove assgined agents from owners and listings",
      "status": "Done",
      "net_days": 28.61,
      "gross_days": 28.61,
      "excluded_days": 0.0,
      "cost_egp": 100135.0,
      "is_complete": true,
      "num_spans": 1
    },
    {
      "key": "NCRM-378",
      "summary": "Listing status to be available from the listings page",
      "status": "Done",
      "net_days": 27.86,
      "gross_days": 27.86,
      "excluded_days": 0.0,
      "cost_egp": 97510.0,
      "is_complete": true,
      "num_spans": 1
    },
    {
      "key": "NCRM-379",
      "summary": "Filter on the listing status",
      "status": "Done",
      "net_days": 27.86,
      "gross_days": 27.86,
      "excluded_days": 0.0,
      "cost_egp": 97510.0,
      "is_complete": true,
      "num_spans": 1
    },
    {
      "key": "NCRM-380",
      "summary": "filter for lead source (CRM, Lists, both)",
      "status": "Done",
      "net_days": 28.49,
      "gross_days": 28.49,
      "excluded_days": 0.0,
      "cost_egp": 99715.0,
      "is_complete": true,
      "num_spans": 1
    },
    {
      "key": "NCRM-381",
      "summary": "Add fields to listing table",
      "status": "Done",
      "net_days": 25.19,
      "gross_days": 25.19,
      "excluded_days": 0.0,
      "cost_egp": 88165.0,
      "is_complete": true,
      "num_spans": 1
    },
    {
      "key": "NCRM-382",
      "summary": "Add statuses to listings",
      "status": "Done",
      "net_days": 0.0,
      "gross_days": 0.0,
      "excluded_days": 0.0,
      "cost_egp": 0.0,
      "is_complete": true,
      "num_spans": 0
    },
    {
      "key": "NCRM-387",
      "summary": "Price updates to create a comment",
      "status": "Done",
      "net_days": 6.65,
      "gross_days": 6.65,
      "excluded_days": 0.0,
      "cost_egp": 23275.0,
      "is_complete": true,
      "num_spans": 1
    },
    {
      "key": "NCRM-388",
      "summary": "Object object for phone numbers bug",
      "status": "Done",
      "net_days": 0.0,
      "gross_days": 0.0,
      "excluded_days": 0.0,
      "cost_egp": 0.0,
      "is_complete": true,
      "num_spans": 0
    },
    {
      "key": "NCRM-389",
      "summary": "Image access from the CRM",
      "status": "Done",
      "net_days": 7.15,
      "gross_days": 7.15,
      "excluded_days": 0.0,
      "cost_egp": 25025.0,
      "is_complete": true,
      "num_spans": 1
    },
    {
      "key": "NCRM-390",
      "summary": "Pricing triggers \"Needs to be contacted (resale)\" Status update",
      "status": "Done",
      "net_days": 3.53,
      "gross_days": 3.53,
      "excluded_days": 0.0,
      "cost_egp": 12355.0,
      "is_complete": true,
      "num_spans": 1
    },
    {
      "key": "NCRM-395",
      "summary": "publish delete listing event",
      "status": "Done",
      "net_days": 0.0,
      "gross_days": 0.0,
      "excluded_days": 0.0,
      "cost_egp": 0.0,
      "is_complete": true,
      "num_spans": 0
    },
    {
      "key": "NCRM-396",
      "summary": "send rest of data(garden, roof, land, ...) in publish create/update events",
      "status": "Done",
      "net_days": 0.0,
      "gross_days": 0.0,
      "excluded_days": 0.0,
      "cost_egp": 0.0,
      "is_complete": true,
      "num_spans": 0
    },
    {
      "key": "NCRM-397",
      "summary": "include email of user that initiate the action in publish events",
      "status": "Done",
      "net_days": 0.0,
      "gross_days": 0.0,
      "excluded_days": 0.0,
      "cost_egp": 0.0,
      "is_complete": true,
      "num_spans": 0
    },
    {
      "key": "NCRM-398",
      "summary": "send images in create/update listing",
      "status": "Done",
      "net_days": 0.0,
      "gross_days": 0.0,
      "excluded_days": 0.0,
      "cost_egp": 0.0,
      "is_complete": true,
      "num_spans": 0
    },
    {
      "key": "NCRM-399",
      "summary": "update/adding images in update listing modal",
      "status": "Done",
      "net_days": 0.0,
      "gross_days": 0.0,
      "excluded_days": 0.0,
      "cost_egp": 0.0,
      "is_complete": true,
      "num_spans": 0
    },
    {
      "key": "NCRM-400",
      "summary": "All details in comment create lead - update existing lead",
      "status": "Done",
      "net_days": 0.0,
      "gross_days": 0.0,
      "excluded_days": 0.0,
      "cost_egp": 0.0,
      "is_complete": true,
      "num_spans": 0
    },
    {
      "key": "NCRM-401",
      "summary": "Adding Owners' statuses",
      "status": "Done",
      "net_days": 23.86,
      "gross_days": 23.86,
      "excluded_days": 0.0,
      "cost_egp": 83510.0,
      "is_complete": true,
      "num_spans": 1
    },
    {
      "key": "NCRM-411",
      "summary": "website assign new lead to assignee with the original seller lead ",
      "status": "Done",
      "net_days": 12.07,
      "gross_days": 12.07,
      "excluded_days": 0.0,
      "cost_egp": 42245.0,
      "is_complete": true,
      "num_spans": 1
    }
  ]
}